qformat/__init__.py
qformat/version.py
qformat-0.1.0.dist-info/METADATA
qformat-0.1.0.dist-info/WHEEL
qformat-0.1.0.dist-info/top_level.txt
qformat-0.1.0.dist-info/RECORD
