Metadata-Version: 2.1
Name: qformat
Version: 0.1.0
Summary: qformat
Home-page: http://github.com/zhiqingxiao/qformat/
Author: Zhiqing Xiao
Author-email: xzq.xiaozhiqing@gmail.com
Classifier: Programming Language :: Python
Classifier: Intended Audience :: Science/Research
